airflow_provider_cloe/__init__.py
airflow_provider_cloe/operators/__init__.py
airflow_provider_cloe/operators/dbtofs/__init__.py
airflow_provider_cloe/operators/dbtofs/base.py
airflow_provider_cloe/operators/dbtofs/local.py
airflow_provider_cloe/operators/dbtofs/odbc/__init__.py
airflow_provider_cloe/operators/dbtofs/odbc/local.py
airflow_provider_cloe/operators/dbtofs/snowflake/__init__.py
airflow_provider_cloe/operators/dbtofs/snowflake/local.py
airflow_provider_cloe/operators/fstodb/__init__.py
airflow_provider_cloe/operators/fstodb/base.py
airflow_provider_cloe/operators/fstodb/local.py
airflow_provider_cloe/operators/fstodb/odbc/__init__.py
airflow_provider_cloe/operators/fstodb/odbc/local.py
airflow_provider_cloe/operators/fstodb/snowflake/__init__.py
airflow_provider_cloe/operators/fstodb/snowflake/remote.py
airflow_provider_cloe/templates/__init__.py
airflow_provider_cloe/templates/filecatalog_insert_files.sql.j2
airflow_provider_cloe/templates/filecatalog_select_files.sql.j2
airflow_provider_cloe/templates/filecatalog_update_files.sql.j2
airflow_provider_cloe/templates/snowflake_insert_into_from_raw.sql.j2
airflow_provider_cloe/templates/stage_describe.sql.j2
airflow_provider_cloe/templates/stage_list.sql.j2
airflow_provider_cloe/templates/table_copy_into.sql.j2
airflow_provider_cloe/templates/table_insert_into.sql.j2
airflow_provider_cloe/templates/table_truncate.sql.j2
airflow_provider_cloe/templates/update_stage_filename.sql.j2
airflow_provider_cloe/utils/__init__.py
airflow_provider_cloe/utils/templating_engine/__init__.py
airflow_provider_cloe/utils/templating_engine/sql_templates.py
airflow_provider_cloe-20221202.13.dist-info/METADATA
airflow_provider_cloe-20221202.13.dist-info/WHEEL
airflow_provider_cloe-20221202.13.dist-info/entry_points.txt
airflow_provider_cloe-20221202.13.dist-info/top_level.txt
airflow_provider_cloe-20221202.13.dist-info/RECORD
